{
  "paper": "论太虚大师对朱熹等理学家辟佛思想的回应",
  "dimensional_terms": [
    {
      "term": "儒佛關係",
      "category": [
        "對話傳統"
      ],
      "rationale": "全文主题：太虚对朱熹等理学家辟佛思想的系统性回应——利人利己的佛教真谛"
    },
    {
      "term": "居士佛教",
      "category": [
        "制度實踐"
      ],
      "rationale": "居士佛教作为破除世俗批评的制度措施——在家修行者的社会角色"
    },
    {
      "term": "佛教倫理學",
      "category": [
        "義理體系"
      ],
      "rationale": "「利人方能利己」——太虚以佛教伦理回应儒家的自私之厌批评"
    },
    {
      "term": "判教",
      "category": [
        "方法論立場"
      ],
      "rationale": "「立足佛教理论，吸收世俗思想」——以判教方法统摄儒家思想入佛教框架"
    }
  ]
}