{
  "title": "起信论与唯识学的会通",
  "author": "",
  "keywords": "",
  "abstract": "",
  "headings": [
    "一、真如与本觉",
    "二、如来藏与众生心",
    "三、熏习义之新解",
    "四、如来藏缘起之地位"
  ],
  "intro": "《起信论》与唯识宗，在真如概念的理解上是不同的。《起信论》把真如视作真如心（真心)，唯识宗则将真如视作缘起性空义上的正智所缘境。\n\n在唯识宗那里，真如作为圣知所缘境，也即指诸法本性、诸法实相。此法性、实相，虽然遍为诸染净法之本性，但就其本义来看，是指诸法清净本性，是圣智所缘境，只在净依他中呈现。在众生位上，由于意识的遍计执取，并不能呈现真如实相之境。而《起信论》则讲真如心、心真如，真如也即诸法无性之性，真如心、心真如即是将心与真如合一，以心统摄诸法之无性之性。《起信论》之真如性，本来也指诸法本性、实相，也即圣智所缘境，只是它将圣智所缘境收摄于众生心中，认为众生本来就有呈现此真如理境的智心，也即如来藏自性清净心。这其实是为众生成佛找到了先天的超越依据。如何来统合《起信论》与唯识宗关于真如概念理解上的不同，这是太虚作《起信论唯识释》所要解决的一个重要问题。\n\n作为宗奉唯识思想的太虚法师，他对真如概念的理解首先也是指正智所缘境。他在解释《起信论》中的“是心真如相即示摩诃衍体故”时说：\n\n“大乘以由二空智所显真如为自体，是菩萨心根本智现行能照达真如，故能示摩诃\n\n“二空”即人我执、法我执二空。这人法二种执，是染污世界形成的根本。正是这两种执，才使得众生不能证见到世界的真相。真如即是世界的真相。众生只有获得正智，破除人法二执(二空)，才能证见真如实相。真如即是摩诃衍大乘体，也就是正智所缘境。\n\n对于《起信论》真如心，太虚则认为“根本智证真如曰心真如”®，即真如心。此境智合一之真如心，也即《起信论》所讲的一心二门中的心真如门。\n\n此真如门在《起信论》（指法藏《起信论》真心系）中不仅指佛果一法界大总相法门体，而且就其不分而分之智心而言，也指众生本有之法体觉心，即是指心生灭门中的本觉义。本觉也就是心体，它是《起信论》所讲的众生成佛之所以可能的根据，是众生心中之法身：“所言觉者，谓心体离念。离念相者，等虚空界，无所不遍，法界一相，即是如来平等法身。依此法身，说名本觉”④。\n\n太虚所讲的境智合一之真如心，虽在佛果上同于《起信论》（指法藏理解的《起信论》)，但他并不认为在众生位（指异生位之众生），也有此佛果法身。在众生位并不能讲境智合一，因为众生位二执障深重，尚未能开显智心，更未能呈现真如理境，所以不能讲众生本有真如心。在太虚看来，真如本是指法性，它是迷悟所依，并且是所缘境意义上的所依，不是法藏所讲的《起信论》本觉心体意义上的所依。他指出，法藏所理解的《起信论》本觉心体是对《起信论》及佛理的误解。佛经经常出现“众生本来清净相”、“众生无始本无虚妄分别心念，与如来等”，其实是指释尊成佛时，回观众生，众生如来究竟觉中所显，并非指众生真的本来是佛，与如来等。他批评法藏以《起信论》为理论来源的法界还源观是：“不知此义，但依佛之自居智境，说诸众生无始不觉，实依如来觉心而起，实有始起之期可得。若贤首家法界还源观等，则众生虽可还如来觉心源而成佛，其如佛仍将从众生不觉心流成众生河。”®",
  "conclusion": "①9参见窥基著《大乘法苑义林章·唯识义林章》《大正藏》 第 45 册第 260页。\n\n②关于唯识宗之如来藏理体义，可参看牟宗三著《佛性与般若》上册第320-325页（台湾学生书局1989年版5版)。\n\n②参见真谛译《大乘起信论》大正藏第32册第576页。\n\n②参见真谛译《大乘起信论》大正藏第32册第578页。\n\n参见真谛译《大乘起信论》大正藏第32册第578页。\n\n近人欧阳近无关于唯识宗真如概念与《起信论》真如概念的差别作过详尽的简别。他说：“真如超绝言思，本不可名，强名之为真如，而亦但是简别。真简有漏虚妄，又简遍计所执；如简无漏变异，又简依他生灭。此之所简，间即有遮，盖恐行者于二空所显圣智所行境界不如理思，犹作种种有漏虚妄遍计所执，或无漏变异依他生灭之想，故以真义如义遮之。是故真如之言，并非表白有其别用。古今人多昧解，直视真如二字为表，益以真如受熏缘起万法之说，遂至颠倒支离莫辩所以，吁可哀也！真如缘起之说出于《起信论》。”(《欧阳竟无集》第104-105页中国社会科学出版社 1995 年版)。\n\n③唯识宗所讲的第八识根据修行阶位的不同，可有不同的名称，《成唯识论》卷3共列有七种名称：心（由种种法熏习种子所积集)，阿陀那(执持种子及色根令不坏)，所知依（能为染净法所依止)，种子识（能任持染净法种子)，阿赖耶(摄藏杂染品种子)，异熟识(能引生善不善业异热果)，无垢识(最极清净无漏法所依，此名唯在如来地有)。(参见大正藏第31册第13页）太虚认为，华严宗所讲的法界真心缘起，其实就是指佛界无垢识起现的最极清净无漏法界。\n\n③参见太虚著《法相唯识学》下册第430页。",
  "char_count": 11030,
  "digest_chars": 2149,
  "type": "paper",
  "_file": "起信论与唯识学的会通——太虚法师《起信论唯识释》思想研究-单正齐.md"
}